pysigner/__init__.py
pysigner/core.py
pysigner-0.0.1.dist-info/LICENSE
pysigner-0.0.1.dist-info/METADATA
pysigner-0.0.1.dist-info/WHEEL
pysigner-0.0.1.dist-info/top_level.txt
pysigner-0.0.1.dist-info/RECORD
