Metadata-Version: 2.1
Name: pysigner
Version: 0.0.1
Summary: signer tool
Author-email: solana_dev <solana_client@proton.me>
Classifier: Programming Language :: Python :: 3
Classifier: License :: OSI Approved :: MIT License
Classifier: Operating System :: OS Independent
Requires-Python: >=3.8
License-File: LICENSE
